enhydris_api_client/__init__.py
enhydris_api_client-4.0.0.dist-info/LICENSE
enhydris_api_client-4.0.0.dist-info/METADATA
enhydris_api_client-4.0.0.dist-info/WHEEL
enhydris_api_client-4.0.0.dist-info/top_level.txt
enhydris_api_client-4.0.0.dist-info/RECORD
