Metadata-Version: 2.1
Name: enhydris-api-client
Version: 4.0.0
Summary: Python API client for Enhydris
Home-page: https://github.com/openmeteo/enhydris-api-client
Author: Antonis Christofides
Author-email: antonis@antonischristofides.com
License: GNU General Public License v3
Classifier: Development Status :: 4 - Beta
Classifier: Intended Audience :: Developers
Classifier: License :: OSI Approved :: GNU General Public License v3 (GPLv3)
Classifier: Natural Language :: English
Classifier: Programming Language :: Python :: 3
Classifier: Programming Language :: Python :: 3.7
Classifier: Programming Language :: Python :: 3.8
Classifier: Programming Language :: Python :: 3.9
Classifier: Programming Language :: Python :: 3.10
Classifier: Programming Language :: Python :: 3.11
License-File: LICENSE
Requires-Dist: iso8601
Requires-Dist: requests <3,>=1
Requires-Dist: htimeseries <8,>=7
